2x4 Decoder/decoder_2x4.v
module decoder_2x4 ( sel,y,i );

input [1:0] sel;
output reg [3:0] y;
input i;

always @ (sel,i) begin
    if (sel==2'b00) y= {i,3'b000};
    else if (sel==2'b01) y= {1'b0,i,2'b00};
    else if (sel==2'b10) y= {2'b00,i,1'b0};
    else if (sel==2'b11) y= {3'b000,i};
 end

    
endmodule

2x4 Decoder/decoder_2x4_tb.v
`include "decoder_2x4.v"
module test ();
reg [1:0] Sel;
reg I;
wire [3:0] out;

integer i,j;
decoder_2x4 dut (Sel,out,I);   

    initial begin
        $dumpfile("decoder.vcd");
        $dumpvars(1);
        for (i=0;i<4;i=i+1) begin
             for (j=0;j<2;j=j+1) begin
                 #5;
                 Sel=i;
                 I=j;
             end
            
        end

    end
endmodule

2x4 Decoder/decoder.vcd
$date
	Tue May 11 02:17:23 2021
$end
$version
	Icarus Verilog
$end
$timescale
	1s
$end
$scope module test $end
$var wire 4 ! out [3:0] $end
$var reg 1 " I $end
$var reg 2 # Sel [1:0] $end
$var integer 32 $ i [31:0] $end
$var integer 32 % j [31:0] $end
$upscope $end
$enddefinitions $end
#0
$dumpvars
b0 %
b0 $
bx #
x"
bx !
$end
#5
b0 !
b1 %
0"
b0 #
#10
b1000 !
b1 $
b0 %
1"
#15
b0 !
b1 %
0"
b1 #
#20
b100 !
b10 $
b0 %
1"
#25
b0 !
b1 %
0"
b10 #
#30
b10 !
b11 $
b0 %
1"
#35
b0 !
b1 %
0"
b11 #
#40
b1 !
b100 $
b10 %
1"
