jk_ff/jk_ff.v
module jk_ff (clk,reset,j,k,q,qbar);

input clk,reset,j,k;
output reg q;
output qbar;

assign qbar =~q;

always @(posedge clk) begin
    if(reset) q<=1'b0;
    else
        case ({j,k})
        2'b01  : q<=1'b0;
        2'b10  : q<=1'b1;
        2'b11  : q<= ~q;
        endcase   
end
    
endmodule

jk_ff/jk_tb.v
`include "jk_ff.v"

module test ();

reg clk,reset,j,k;
wire q, qbar;  
integer i=0;
jk_ff sut  (clk,reset,j,k,q,qbar);


initial begin
    clk=0;
    reset=0;
    #3;
    reset=1;
    #10;
    repeat (8) begin
       {j,k,reset} =i;
       #10;
       i=i+1; 
    end
    #10;
    $finish;
end

initial begin
    forever #5 clk=!clk;
end

initial begin
    $dumpfile("fi.vcd");
    $dumpvars(0);
end

endmodule

jk_ff/fi.vcd
$date
	Sat May 29 23:43:43 2021
$end
$version
	Icarus Verilog
$end
$timescale
	1s
$end
$scope module test $end
$var wire 1 ! qbar $end
$var wire 1 " q $end
$var reg 1 # clk $end
$var reg 1 $ j $end
$var reg 1 % k $end
$var reg 1 & reset $end
$var integer 32 ' i [31:0] $end
$scope module sut $end
$var wire 1 # clk $end
$var wire 1 $ j $end
$var wire 1 % k $end
$var wire 1 ! qbar $end
$var wire 1 & reset $end
$var reg 1 " q $end
$upscope $end
$upscope $end
$enddefinitions $end
#0
$dumpvars
b0 '
0&
x%
x$
0#
x"
x!
$end
#3
1&
#5
1!
0"
1#
#10
0#
#13
0$
0%
0&
#15
1#
#20
0#
#23
1&
b1 '
#25
1#
#30
0#
#33
1%
0&
b10 '
#35
1#
#40
0#
#43
1&
b11 '
#45
1#
#50
0#
#53
1$
0%
0&
b100 '
#55
0!
1"
1#
#60
0#
#63
1&
b101 '
#65
1!
0"
1#
#70
0#
#73
1%
0&
b110 '
#75
0!
1"
1#
#80
0#
#83
1&
b111 '
#85
1!
0"
1#
#90
0#
#93
b1000 '
