4 bit RCA/design.v
`timescale 1ns / 1ps
module fa(
    input a,
    input b,
    input c,
    output sum,
    output carry);
	 wire w2,w3;
	 xor x1(sum,a,b,c);
	 and a1(w1,a,b);
	 and a2(w2,b,c);
	 and a3(w3,a,c);
	 or o1(carry,w1,w2,w3);
endmodule

module fa_4bit (a,b,cin,sum,cout);
input [3:0]a,b;
input cin;
output [3:0] sum;
wire [3:0] c;
output cout;


fa f0 (a[0],b[0],cin,sum[0],c[0]);
fa f1 (a[1],b[1],c[0],sum[1],c[1]);
fa f2 (a[2],b[2],c[1],sum[2],c[2]);
fa f3 (a[3],b[3],c[2],sum[3],cout);

endmodule

4 bit RCA/tb.v
`include "design.v"


module test;

reg [3:0]a,b;
reg cin;
wire [3:0] sum;
wire c;
integer i;

fa_4bit  dur(a,b,cin,sum,c);


initial begin
    $dumpfile("file.vcd");
    $dumpvars(1);
    for ( i=0 ;i<512 ;i=1+i ) 
    begin
        {a,b,cin}=i;
        #5;
        if ( {c,sum}==a+b+cin)
            $display("true");
        else
            $display("False");
        
    end
end
    
endmodule

4 bit RCA/file.vcd
$date
	Fri Jun 11 01:19:55 2021
$end
$version
	Icarus Verilog
$end
$timescale
	1ps
$end
$scope module test $end
$var wire 4 ! sum [3:0] $end
$var wire 1 " c $end
$var reg 4 # a [3:0] $end
$var reg 4 $ b [3:0] $end
$var reg 1 % cin $end
$var integer 32 & i [31:0] $end
$upscope $end
$enddefinitions $end
#0
$dumpvars
b0 &
0%
b0 $
b0 #
0"
b0 !
$end
#5000
b1 !
1%
b1 &
#10000
b1 !
b1 $
0%
b10 &
#15000
b10 !
1%
b11 &
#20000
b10 !
b10 $
0%
b100 &
#25000
b11 !
1%
b101 &
#30000
b11 !
b11 $
0%
b110 &
#35000
b100 !
1%
b111 &
#40000
b100 !
b100 $
0%
b1000 &
#45000
b101 !
1%
b1001 &
#50000
b101 !
b101 $
0%
b1010 &
#55000
b110 !
1%
b1011 &
#60000
b110 !
b110 $
0%
b1100 &
#65000
b111 !
1%
b1101 &
#70000
b111 !
b111 $
0%
b1110 &
#75000
b1000 !
1%
b1111 &
#80000
0"
b1000 !
b1000 $
0%
b10000 &
#85000
b1001 !
1%
b10001 &
#90000
b1001 !
b1001 $
0%
b10010 &
#95000
b1010 !
1%
b10011 &
#100000
b1010 !
b1010 $
0%
b10100 &
#105000
b1011 !
1%
b10101 &
#110000
b1011 !
b1011 $
0%
b10110 &
#115000
b1100 !
1%
b10111 &
#120000
0"
b1100 !
b1100 $
0%
b11000 &
#125000
b1101 !
1%
b11001 &
#130000
b1101 !
b1101 $
0%
b11010 &
#135000
b1110 !
1%
b11011 &
#140000
0"
b1110 !
b1110 $
0%
b11100 &
#145000
b1111 !
1%
b11101 &
#150000
b1111 !
b1111 $
0%
b11110 &
#155000
1"
b0 !
1%
b11111 &
#160000
0"
b1 !
b1 #
b0 $
0%
b100000 &
#165000
b10 !
1%
b100001 &
#170000
b10 !
b1 $
0%
b100010 &
#175000
b11 !
1%
b100011 &
#180000
b11 !
b10 $
0%
b100100 &
#185000
b100 !
1%
b100101 &
#190000
b100 !
b11 $
0%
b100110 &
#195000
b101 !
1%
b100111 &
#200000
b101 !
b100 $
0%
b101000 &
#205000
b110 !
1%
b101001 &
#210000
b110 !
b101 $
0%
b101010 &
#215000
b111 !
1%
b101011 &
#220000
b111 !
b110 $
0%
b101100 &
#225000
b1000 !
1%
b101101 &
#230000
b1000 !
b111 $
0%
b101110 &
#235000
b1001 !
1%
b101111 &
#240000
0"
b1001 !
b1000 $
0%
b110000 &
#245000
b1010 !
1%
b110001 &
#250000
b1010 !
b1001 $
0%
b110010 &
#255000
b1011 !
1%
b110011 &
#260000
b1011 !
b1010 $
0%
b110100 &
#265000
b1100 !
1%
b110101 &
#270000
b1100 !
b1011 $
0%
b110110 &
#275000
b1101 !
1%
b110111 &
#280000
0"
b1101 !
b1100 $
0%
b111000 &
#285000
b1110 !
1%
b111001 &
#290000
b1110 !
b1101 $
0%
b111010 &
#295000
b1111 !
1%
b111011 &
#300000
0"
b1111 !
b1110 $
0%
b111100 &
#305000
1"
b0 !
1%
b111101 &
#310000
1"
b0 !
b1111 $
0%
b111110 &
#315000
b1 !
1%
b111111 &
#320000
0"
b10 !
b10 #
b0 $
0%
b1000000 &
#325000
b11 !
1%
b1000001 &
#330000
b11 !
b1 $
0%
b1000010 &
#335000
b100 !
1%
b1000011 &
#340000
b100 !
b10 $
0%
b1000100 &
#345000
b101 !
1%
b1000101 &
#350000
b101 !
b11 $
0%
b1000110 &
#355000
b110 !
1%
b1000111 &
#360000
b110 !
b100 $
0%
b1001000 &
#365000
b111 !
1%
b1001001 &
#370000
b111 !
b101 $
0%
b1001010 &
#375000
b1000 !
1%
b1001011 &
#380000
b1000 !
b110 $
0%
b1001100 &
#385000
b1001 !
1%
b1001101 &
#390000
b1001 !
b111 $
0%
b1001110 &
#395000
b1010 !
1%
b1001111 &
#400000
0"
b1010 !
b1000 $
0%
b1010000 &
#405000
b1011 !
1%
b1010001 &
#410000
b1011 !
b1001 $
0%
b1010010 &
#415000
b1100 !
1%
b1010011 &
#420000
b1100 !
b1010 $
0%
b1010100 &
#425000
b1101 !
1%
b1010101 &
#430000
b1101 !
b1011 $
0%
b1010110 &
#435000
b1110 !
1%
b1010111 &
#440000
0"
b1110 !
b1100 $
0%
b1011000 &
#445000
b1111 !
1%
b1011001 &
#450000
b1111 !
b1101 $
0%
b1011010 &
#455000
1"
b0 !
1%
b1011011 &
#460000
b0 !
b1110 $
0%
b1011100 &
#465000
b1 !
1%
b1011101 &
#470000
b1 !
b1111 $
0%
b1011110 &
#475000
b10 !
1%
b1011111 &
#480000
0"
b11 !
b11 #
b0 $
0%
b1100000 &
#485000
b100 !
1%
b1100001 &
#490000
b100 !
b1 $
0%
b1100010 &
#495000
b101 !
1%
b1100011 &
#500000
b101 !
b10 $
0%
b1100100 &
#505000
b110 !
1%
b1100101 &
#510000
b110 !
b11 $
0%
b1100110 &
#515000
b111 !
1%
b1100111 &
#520000
b111 !
b100 $
0%
b1101000 &
#525000
b1000 !
1%
b1101001 &
#530000
b1000 !
b101 $
0%
b1101010 &
#535000
b1001 !
1%
b1101011 &
#540000
b1001 !
b110 $
0%
b1101100 &
#545000
b1010 !
1%
b1101101 &
#550000
b1010 !
b111 $
0%
b1101110 &
#555000
b1011 !
1%
b1101111 &
#560000
0"
b1011 !
b1000 $
0%
b1110000 &
#565000
b1100 !
1%
b1110001 &
#570000
b1100 !
b1001 $
0%
b1110010 &
#575000
b1101 !
1%
b1110011 &
#580000
b1101 !
b1010 $
0%
b1110100 &
#585000
b1110 !
1%
b1110101 &
#590000
b1110 !
b1011 $
0%
b1110110 &
#595000
b1111 !
1%
b1110111 &
#600000
0"
b1111 !
b1100 $
0%
b1111000 &
#605000
1"
b0 !
1%
b1111001 &
#610000
1"
b0 !
b1101 $
0%
b1111010 &
#615000
b1 !
1%
b1111011 &
#620000
b1 !
b1110 $
0%
b1111100 &
#625000
b10 !
1%
b1111101 &
#630000
b10 !
b1111 $
0%
b1111110 &
#635000
b11 !
1%
b1111111 &
#640000
0"
b100 !
b100 #
b0 $
0%
b10000000 &
#645000
b101 !
1%
b10000001 &
#650000
b101 !
b1 $
0%
b10000010 &
#655000
b110 !
1%
b10000011 &
#660000
b110 !
b10 $
0%
b10000100 &
#665000
b111 !
1%
b10000101 &
#670000
b111 !
b11 $
0%
b10000110 &
#675000
b1000 !
1%
b10000111 &
#680000
b1000 !
b100 $
0%
b10001000 &
#685000
b1001 !
1%
b10001001 &
#690000
b1001 !
b101 $
0%
b10001010 &
#695000
b1010 !
1%
b10001011 &
#700000
b1010 !
b110 $
0%
b10001100 &
#705000
b1011 !
1%
b10001101 &
#710000
b1011 !
b111 $
0%
b10001110 &
#715000
b1100 !
1%
b10001111 &
#720000
0"
b1100 !
b1000 $
0%
b10010000 &
#725000
b1101 !
1%
b10010001 &
#730000
b1101 !
b1001 $
0%
b10010010 &
#735000
b1110 !
1%
b10010011 &
#740000
0"
b1110 !
b1010 $
0%
b10010100 &
#745000
b1111 !
1%
b10010101 &
#750000
b1111 !
b1011 $
0%
b10010110 &
#755000
1"
b0 !
1%
b10010111 &
#760000
b0 !
b1100 $
0%
b10011000 &
#765000
b1 !
1%
b10011001 &
#770000
b1 !
b1101 $
0%
b10011010 &
#775000
b10 !
1%
b10011011 &
#780000
b10 !
b1110 $
0%
b10011100 &
#785000
b11 !
1%
b10011101 &
#790000
b11 !
b1111 $
0%
b10011110 &
#795000
b100 !
1%
b10011111 &
#800000
0"
b101 !
b101 #
b0 $
0%
b10100000 &
#805000
b110 !
1%
b10100001 &
#810000
b110 !
b1 $
0%
b10100010 &
#815000
b111 !
1%
b10100011 &
#820000
b111 !
b10 $
0%
b10100100 &
#825000
b1000 !
1%
b10100101 &
#830000
b1000 !
b11 $
0%
b10100110 &
#835000
b1001 !
1%
b10100111 &
#840000
b1001 !
b100 $
0%
b10101000 &
#845000
b1010 !
1%
b10101001 &
#850000
b1010 !
b101 $
0%
b10101010 &
#855000
b1011 !
1%
b10101011 &
#860000
b1011 !
b110 $
0%
b10101100 &
#865000
b1100 !
1%
b10101101 &
#870000
b1100 !
b111 $
0%
b10101110 &
#875000
b1101 !
1%
b10101111 &
#880000
0"
b1101 !
b1000 $
0%
b10110000 &
#885000
b1110 !
1%
b10110001 &
#890000
b1110 !
b1001 $
0%
b10110010 &
#895000
b1111 !
1%
b10110011 &
#900000
0"
b1111 !
b1010 $
0%
b10110100 &
#905000
1"
b0 !
1%
b10110101 &
#910000
1"
b0 !
b1011 $
0%
b10110110 &
#915000
b1 !
1%
b10110111 &
#920000
b1 !
b1100 $
0%
b10111000 &
#925000
b10 !
1%
b10111001 &
#930000
b10 !
b1101 $
0%
b10111010 &
#935000
b11 !
1%
b10111011 &
#940000
b11 !
b1110 $
0%
b10111100 &
#945000
b100 !
1%
b10111101 &
#950000
b100 !
b1111 $
0%
b10111110 &
#955000
b101 !
1%
b10111111 &
#960000
0"
b110 !
b110 #
b0 $
0%
b11000000 &
#965000
b111 !
1%
b11000001 &
#970000
b111 !
b1 $
0%
b11000010 &
#975000
b1000 !
1%
b11000011 &
#980000
b1000 !
b10 $
0%
b11000100 &
#985000
b1001 !
1%
b11000101 &
#990000
b1001 !
b11 $
0%
b11000110 &
#995000
b1010 !
1%
b11000111 &
#1000000
b1010 !
b100 $
0%
b11001000 &
#1005000
b1011 !
1%
b11001001 &
#1010000
b1011 !
b101 $
0%
b11001010 &
#1015000
b1100 !
1%
b11001011 &
#1020000
b1100 !
b110 $
0%
b11001100 &
#1025000
b1101 !
1%
b11001101 &
#1030000
b1101 !
b111 $
0%
b11001110 &
#1035000
b1110 !
1%
b11001111 &
#1040000
0"
b1110 !
b1000 $
0%
b11010000 &
#1045000
b1111 !
1%
b11010001 &
#1050000
b1111 !
b1001 $
0%
b11010010 &
#1055000
1"
b0 !
1%
b11010011 &
#1060000
b0 !
b1010 $
0%
b11010100 &
#1065000
b1 !
1%
b11010101 &
#1070000
b1 !
b1011 $
0%
b11010110 &
#1075000
b10 !
1%
b11010111 &
#1080000
b10 !
b1100 $
0%
b11011000 &
#1085000
b11 !
1%
b11011001 &
#1090000
b11 !
b1101 $
0%
b11011010 &
#1095000
b100 !
1%
b11011011 &
#1100000
b100 !
b1110 $
0%
b11011100 &
#1105000
b101 !
1%
b11011101 &
#1110000
b101 !
b1111 $
0%
b11011110 &
#1115000
b110 !
1%
b11011111 &
#1120000
0"
b111 !
b111 #
b0 $
0%
b11100000 &
#1125000
b1000 !
1%
b11100001 &
#1130000
b1000 !
b1 $
0%
b11100010 &
#1135000
b1001 !
1%
b11100011 &
#1140000
b1001 !
b10 $
0%
b11100100 &
#1145000
b1010 !
1%
b11100101 &
#1150000
b1010 !
b11 $
0%
b11100110 &
#1155000
b1011 !
1%
b11100111 &
#1160000
b1011 !
b100 $
0%
b11101000 &
#1165000
b1100 !
1%
b11101001 &
#1170000
b1100 !
b101 $
0%
b11101010 &
#1175000
b1101 !
1%
b11101011 &
#1180000
b1101 !
b110 $
0%
b11101100 &
#1185000
b1110 !
1%
b11101101 &
#1190000
b1110 !
b111 $
0%
b11101110 &
#1195000
b1111 !
1%
b11101111 &
#1200000
0"
b1111 !
b1000 $
0%
b11110000 &
#1205000
1"
b0 !
1%
b11110001 &
#1210000
1"
b0 !
b1001 $
0%
b11110010 &
#1215000
b1 !
1%
b11110011 &
#1220000
b1 !
b1010 $
0%
b11110100 &
#1225000
b10 !
1%
b11110101 &
#1230000
b10 !
b1011 $
0%
b11110110 &
#1235000
b11 !
1%
b11110111 &
#1240000
b11 !
b1100 $
0%
b11111000 &
#1245000
b100 !
1%
b11111001 &
#1250000
b100 !
b1101 $
0%
b11111010 &
#1255000
b101 !
1%
b11111011 &
#1260000
b101 !
b1110 $
0%
b11111100 &
#1265000
b110 !
1%
b11111101 &
#1270000
b110 !
b1111 $
0%
b11111110 &
#1275000
b111 !
1%
b11111111 &
#1280000
0"
b1000 !
b1000 #
b0 $
0%
b100000000 &
#1285000
b1001 !
1%
b100000001 &
#1290000
b1001 !
b1 $
0%
b100000010 &
#1295000
b1010 !
1%
b100000011 &
#1300000
b1010 !
b10 $
0%
b100000100 &
#1305000
b1011 !
1%
b100000101 &
#1310000
b1011 !
b11 $
0%
b100000110 &
#1315000
b1100 !
1%
b100000111 &
#1320000
0"
b1100 !
b100 $
0%
b100001000 &
#1325000
b1101 !
1%
b100001001 &
#1330000
b1101 !
b101 $
0%
b100001010 &
#1335000
b1110 !
1%
b100001011 &
#1340000
0"
b1110 !
b110 $
0%
b100001100 &
#1345000
b1111 !
1%
b100001101 &
#1350000
b1111 !
b111 $
0%
b100001110 &
#1355000
1"
b0 !
1%
b100001111 &
#1360000
b0 !
b1000 $
0%
b100010000 &
#1365000
b1 !
1%
b100010001 &
#1370000
b1 !
b1001 $
0%
b100010010 &
#1375000
b10 !
1%
b100010011 &
#1380000
b10 !
b1010 $
0%
b100010100 &
#1385000
b11 !
1%
b100010101 &
#1390000
b11 !
b1011 $
0%
b100010110 &
#1395000
b100 !
1%
b100010111 &
#1400000
b100 !
b1100 $
0%
b100011000 &
#1405000
b101 !
1%
b100011001 &
#1410000
b101 !
b1101 $
0%
b100011010 &
#1415000
b110 !
1%
b100011011 &
#1420000
b110 !
b1110 $
0%
b100011100 &
#1425000
b111 !
1%
b100011101 &
#1430000
b111 !
b1111 $
0%
b100011110 &
#1435000
b1000 !
1%
b100011111 &
#1440000
0"
b1001 !
b1001 #
b0 $
0%
b100100000 &
#1445000
b1010 !
1%
b100100001 &
#1450000
b1010 !
b1 $
0%
b100100010 &
#1455000
b1011 !
1%
b100100011 &
#1460000
b1011 !
b10 $
0%
b100100100 &
#1465000
b1100 !
1%
b100100101 &
#1470000
b1100 !
b11 $
0%
b100100110 &
#1475000
b1101 !
1%
b100100111 &
#1480000
0"
b1101 !
b100 $
0%
b100101000 &
#1485000
b1110 !
1%
b100101001 &
#1490000
b1110 !
b101 $
0%
b100101010 &
#1495000
b1111 !
1%
b100101011 &
#1500000
0"
b1111 !
b110 $
0%
b100101100 &
#1505000
1"
b0 !
1%
b100101101 &
#1510000
1"
b0 !
b111 $
0%
b100101110 &
#1515000
b1 !
1%
b100101111 &
#1520000
b1 !
b1000 $
0%
b100110000 &
#1525000
b10 !
1%
b100110001 &
#1530000
b10 !
b1001 $
0%
b100110010 &
#1535000
b11 !
1%
b100110011 &
#1540000
b11 !
b1010 $
0%
b100110100 &
#1545000
b100 !
1%
b100110101 &
#1550000
b100 !
b1011 $
0%
b100110110 &
#1555000
b101 !
1%
b100110111 &
#1560000
b101 !
b1100 $
0%
b100111000 &
#1565000
b110 !
1%
b100111001 &
#1570000
b110 !
b1101 $
0%
b100111010 &
#1575000
b111 !
1%
b100111011 &
#1580000
b111 !
b1110 $
0%
b100111100 &
#1585000
b1000 !
1%
b100111101 &
#1590000
b1000 !
b1111 $
0%
b100111110 &
#1595000
b1001 !
1%
b100111111 &
#1600000
0"
b1010 !
b1010 #
b0 $
0%
b101000000 &
#1605000
b1011 !
1%
b101000001 &
#1610000
b1011 !
b1 $
0%
b101000010 &
#1615000
b1100 !
1%
b101000011 &
#1620000
b1100 !
b10 $
0%
b101000100 &
#1625000
b1101 !
1%
b101000101 &
#1630000
b1101 !
b11 $
0%
b101000110 &
#1635000
b1110 !
1%
b101000111 &
#1640000
0"
b1110 !
b100 $
0%
b101001000 &
#1645000
b1111 !
1%
b101001001 &
#1650000
b1111 !
b101 $
0%
b101001010 &
#1655000
1"
b0 !
1%
b101001011 &
#1660000
b0 !
b110 $
0%
b101001100 &
#1665000
b1 !
1%
b101001101 &
#1670000
b1 !
b111 $
0%
b101001110 &
#1675000
b10 !
1%
b101001111 &
#1680000
b10 !
b1000 $
0%
b101010000 &
#1685000
b11 !
1%
b101010001 &
#1690000
b11 !
b1001 $
0%
b101010010 &
#1695000
b100 !
1%
b101010011 &
#1700000
b100 !
b1010 $
0%
b101010100 &
#1705000
b101 !
1%
b101010101 &
#1710000
b101 !
b1011 $
0%
b101010110 &
#1715000
b110 !
1%
b101010111 &
#1720000
b110 !
b1100 $
0%
b101011000 &
#1725000
b111 !
1%
b101011001 &
#1730000
b111 !
b1101 $
0%
b101011010 &
#1735000
b1000 !
1%
b101011011 &
#1740000
b1000 !
b1110 $
0%
b101011100 &
#1745000
b1001 !
1%
b101011101 &
#1750000
b1001 !
b1111 $
0%
b101011110 &
#1755000
b1010 !
1%
b101011111 &
#1760000
0"
b1011 !
b1011 #
b0 $
0%
b101100000 &
#1765000
b1100 !
1%
b101100001 &
#1770000
b1100 !
b1 $
0%
b101100010 &
#1775000
b1101 !
1%
b101100011 &
#1780000
b1101 !
b10 $
0%
b101100100 &
#1785000
b1110 !
1%
b101100101 &
#1790000
b1110 !
b11 $
0%
b101100110 &
#1795000
b1111 !
1%
b101100111 &
#1800000
0"
b1111 !
b100 $
0%
b101101000 &
#1805000
1"
b0 !
1%
b101101001 &
#1810000
1"
b0 !
b101 $
0%
b101101010 &
#1815000
b1 !
1%
b101101011 &
#1820000
b1 !
b110 $
0%
b101101100 &
#1825000
b10 !
1%
b101101101 &
#1830000
b10 !
b111 $
0%
b101101110 &
#1835000
b11 !
1%
b101101111 &
#1840000
b11 !
b1000 $
0%
b101110000 &
#1845000
b100 !
1%
b101110001 &
#1850000
b100 !
b1001 $
0%
b101110010 &
#1855000
b101 !
1%
b101110011 &
#1860000
b101 !
b1010 $
0%
b101110100 &
#1865000
b110 !
1%
b101110101 &
#1870000
b110 !
b1011 $
0%
b101110110 &
#1875000
b111 !
1%
b101110111 &
#1880000
b111 !
b1100 $
0%
b101111000 &
#1885000
b1000 !
1%
b101111001 &
#1890000
b1000 !
b1101 $
0%
b101111010 &
#1895000
b1001 !
1%
b101111011 &
#1900000
b1001 !
b1110 $
0%
b101111100 &
#1905000
b1010 !
1%
b101111101 &
#1910000
b1010 !
b1111 $
0%
b101111110 &
#1915000
b1011 !
1%
b101111111 &
#1920000
0"
b1100 !
b1100 #
b0 $
0%
b110000000 &
#1925000
b1101 !
1%
b110000001 &
#1930000
b1101 !
b1 $
0%
b110000010 &
#1935000
b1110 !
1%
b110000011 &
#1940000
0"
b1110 !
b10 $
0%
b110000100 &
#1945000
b1111 !
1%
b110000101 &
#1950000
b1111 !
b11 $
0%
b110000110 &
#1955000
1"
b0 !
1%
b110000111 &
#1960000
b0 !
b100 $
0%
b110001000 &
#1965000
b1 !
1%
b110001001 &
#1970000
b1 !
b101 $
0%
b110001010 &
#1975000
b10 !
1%
b110001011 &
#1980000
b10 !
b110 $
0%
b110001100 &
#1985000
b11 !
1%
b110001101 &
#1990000
b11 !
b111 $
0%
b110001110 &
#1995000
b100 !
1%
b110001111 &
#2000000
b100 !
b1000 $
0%
b110010000 &
#2005000
b101 !
1%
b110010001 &
#2010000
b101 !
b1001 $
0%
b110010010 &
#2015000
b110 !
1%
b110010011 &
#2020000
b110 !
b1010 $
0%
b110010100 &
#2025000
b111 !
1%
b110010101 &
#2030000
b111 !
b1011 $
0%
b110010110 &
#2035000
b1000 !
1%
b110010111 &
#2040000
b1000 !
b1100 $
0%
b110011000 &
#2045000
b1001 !
1%
b110011001 &
#2050000
b1001 !
b1101 $
0%
b110011010 &
#2055000
b1010 !
1%
b110011011 &
#2060000
b1010 !
b1110 $
0%
b110011100 &
#2065000
b1011 !
1%
b110011101 &
#2070000
b1011 !
b1111 $
0%
b110011110 &
#2075000
b1100 !
1%
b110011111 &
#2080000
0"
b1101 !
b1101 #
b0 $
0%
b110100000 &
#2085000
b1110 !
1%
b110100001 &
#2090000
b1110 !
b1 $
0%
b110100010 &
#2095000
b1111 !
1%
b110100011 &
#2100000
0"
b1111 !
b10 $
0%
b110100100 &
#2105000
1"
b0 !
1%
b110100101 &
#2110000
1"
b0 !
b11 $
0%
b110100110 &
#2115000
b1 !
1%
b110100111 &
#2120000
b1 !
b100 $
0%
b110101000 &
#2125000
b10 !
1%
b110101001 &
#2130000
b10 !
b101 $
0%
b110101010 &
#2135000
b11 !
1%
b110101011 &
#2140000
b11 !
b110 $
0%
b110101100 &
#2145000
b100 !
1%
b110101101 &
#2150000
b100 !
b111 $
0%
b110101110 &
#2155000
b101 !
1%
b110101111 &
#2160000
b101 !
b1000 $
0%
b110110000 &
#2165000
b110 !
1%
b110110001 &
#2170000
b110 !
b1001 $
0%
b110110010 &
#2175000
b111 !
1%
b110110011 &
#2180000
b111 !
b1010 $
0%
b110110100 &
#2185000
b1000 !
1%
b110110101 &
#2190000
b1000 !
b1011 $
0%
b110110110 &
#2195000
b1001 !
1%
b110110111 &
#2200000
b1001 !
b1100 $
0%
b110111000 &
#2205000
b1010 !
1%
b110111001 &
#2210000
b1010 !
b1101 $
0%
b110111010 &
#2215000
b1011 !
1%
b110111011 &
#2220000
b1011 !
b1110 $
0%
b110111100 &
#2225000
b1100 !
1%
b110111101 &
#2230000
b1100 !
b1111 $
0%
b110111110 &
#2235000
b1101 !
1%
b110111111 &
#2240000
0"
b1110 !
b1110 #
b0 $
0%
b111000000 &
#2245000
b1111 !
1%
b111000001 &
#2250000
b1111 !
b1 $
0%
b111000010 &
#2255000
1"
b0 !
1%
b111000011 &
#2260000
b0 !
b10 $
0%
b111000100 &
#2265000
b1 !
1%
b111000101 &
#2270000
b1 !
b11 $
0%
b111000110 &
#2275000
b10 !
1%
b111000111 &
#2280000
b10 !
b100 $
0%
b111001000 &
#2285000
b11 !
1%
b111001001 &
#2290000
b11 !
b101 $
0%
b111001010 &
#2295000
b100 !
1%
b111001011 &
#2300000
b100 !
b110 $
0%
b111001100 &
#2305000
b101 !
1%
b111001101 &
#2310000
b101 !
b111 $
0%
b111001110 &
#2315000
b110 !
1%
b111001111 &
#2320000
b110 !
b1000 $
0%
b111010000 &
#2325000
b111 !
1%
b111010001 &
#2330000
b111 !
b1001 $
0%
b111010010 &
#2335000
b1000 !
1%
b111010011 &
#2340000
b1000 !
b1010 $
0%
b111010100 &
#2345000
b1001 !
1%
b111010101 &
#2350000
b1001 !
b1011 $
0%
b111010110 &
#2355000
b1010 !
1%
b111010111 &
#2360000
b1010 !
b1100 $
0%
b111011000 &
#2365000
b1011 !
1%
b111011001 &
#2370000
b1011 !
b1101 $
0%
b111011010 &
#2375000
b1100 !
1%
b111011011 &
#2380000
b1100 !
b1110 $
0%
b111011100 &
#2385000
b1101 !
1%
b111011101 &
#2390000
b1101 !
b1111 $
0%
b111011110 &
#2395000
b1110 !
1%
b111011111 &
#2400000
0"
b1111 !
b1111 #
b0 $
0%
b111100000 &
#2405000
1"
b0 !
1%
b111100001 &
#2410000
1"
b0 !
b1 $
0%
b111100010 &
#2415000
b1 !
1%
b111100011 &
#2420000
b1 !
b10 $
0%
b111100100 &
#2425000
b10 !
1%
b111100101 &
#2430000
b10 !
b11 $
0%
b111100110 &
#2435000
b11 !
1%
b111100111 &
#2440000
b11 !
b100 $
0%
b111101000 &
#2445000
b100 !
1%
b111101001 &
#2450000
b100 !
b101 $
0%
b111101010 &
#2455000
b101 !
1%
b111101011 &
#2460000
b101 !
b110 $
0%
b111101100 &
#2465000
b110 !
1%
b111101101 &
#2470000
b110 !
b111 $
0%
b111101110 &
#2475000
b111 !
1%
b111101111 &
#2480000
b111 !
b1000 $
0%
b111110000 &
#2485000
b1000 !
1%
b111110001 &
#2490000
b1000 !
b1001 $
0%
b111110010 &
#2495000
b1001 !
1%
b111110011 &
#2500000
b1001 !
b1010 $
0%
b111110100 &
#2505000
b1010 !
1%
b111110101 &
#2510000
b1010 !
b1011 $
0%
b111110110 &
#2515000
b1011 !
1%
b111110111 &
#2520000
b1011 !
b1100 $
0%
b111111000 &
#2525000
b1100 !
1%
b111111001 &
#2530000
b1100 !
b1101 $
0%
b111111010 &
#2535000
b1101 !
1%
b111111011 &
#2540000
b1101 !
b1110 $
0%
b111111100 &
#2545000
b1110 !
1%
b111111101 &
#2550000
b1110 !
b1111 $
0%
b111111110 &
#2555000
b1111 !
1%
b111111111 &
#2560000
b1000000000 &
